singtown_ai/__init__.py
singtown_ai/client.py
singtown_ai/exporter.py
singtown_ai/type.py
singtown_ai/watcher.py
singtown_ai-1.9.3.dist-info/METADATA
singtown_ai-1.9.3.dist-info/WHEEL
singtown_ai-1.9.3.dist-info/top_level.txt
singtown_ai-1.9.3.dist-info/RECORD
