Metadata-Version: 2.4
Name: singtown_ai
Version: 1.9.3
Summary: SingTown AI Python Client
Requires-Python: >=3.9
Requires-Dist: pydantic
Requires-Dist: requests
Requires-Dist: requests-mock
Requires-Dist: pyyaml
Requires-Dist: fsspec
Requires-Dist: aiohttp
